{
  "showLegend": false,
  "contextMenu": {
    "ZoomTo": true,
    "Transparency": true,
    "EnableOrDisablePopup": true,
    "MoveupOrMovedown": true,
    "OpenAttributeTable": true,
    "DescriptionOrShowItemDetailsOrDownload": true
  },
  "layerOptions": {
    "SkredSnoAktR_6249": {
      "display": false
    },
    "SkredSnoAktR_6249_0": {
      "display": true
    },
    "SkredSnoAktR_6249_1": {
      "display": true
    },
    "SkredSnoAktR_6249_2": {
      "display": true
    },
    "SkredHendelser_473": {
      "display": false
    },
    "SkredHendelser_473_0": {
      "display": true
    },
    "SkredHendelser_473_1": {
      "display": true
    },
    "SkredHendelser_473_2": {
      "display": true
    },
    "SkredHendelser_473_3": {
      "display": true
    },
    "SkredHendelser_473_4": {
      "display": true
    },
    "SkredHendelser_473_5": {
      "display": true
    },
    "SkredHendelser_473_6": {
      "display": true
    },
    "SkredSnoSteinAkt_9580": {
      "display": false
    },
    "SkredSnoSteinAkt_9580_0": {
      "display": true
    },
    "SkredSnoSteinAkt_9580_1": {
      "display": true
    },
    "SkredSnoSteinAkt_9580_2": {
      "display": true
    },
    "SkredKvikkleire1_6024": {
      "display": false
    },
    "SkredKvikkleire1_6024_0": {
      "display": true
    },
    "SkredKvikkleire1_6024_1": {
      "display": true
    },
    "SkredKvikkleire1_6024_2": {
      "display": true
    },
    "Skredfaresoner1_2281": {
      "display": false
    },
    "Skredfaresoner1_2281_0": {
      "display": true
    },
    "Skredfaresoner1_2281_1": {
      "display": true
    },
    "Skredfaresoner1_2281_2": {
      "display": true
    },
    "Skredfaresoner1_2281_3": {
      "display": true
    },
    "Fjellskred_4768": {
      "display": false
    },
    "Fjellskred_4768_0": {
      "display": true
    },
    "Fjellskred_4768_1": {
      "display": true
    },
    "Fjellskred_4768_2": {
      "display": true
    },
    "Fjellskred_4768_3": {
      "display": true
    },
    "Fjellskred_4768_4": {
      "display": true
    },
    "Fjellskred_4768_5": {
      "display": true
    },
    "Fjellskred_4768_6": {
      "display": true
    },
    "Fjellskred_4768_7": {
      "display": true
    },
    "Fjellskred_4768_8": {
      "display": true
    },
    "Fjellskred_4768_9": {
      "display": true
    },
    "Sikringstiltak_7728": {
      "display": false
    },
    "Sikringstiltak_7728_0": {
      "display": true
    },
    "FlomAktR_5316": {
      "display": false
    },
    "FlomAktR_5316_0": {
      "display": true
    },
    "FlomAktR_5316_1": {
      "display": true
    },
    "SkredJordFlomAktR1_9470": {
      "display": false
    },
    "SkredJordFlomAktR1_9470_0": {
      "display": true
    },
    "SkredJordFlomAktR1_9470_1": {
      "display": true
    },
    "SkredSteinAktR_3146": {
      "display": false
    },
    "SkredSteinAktR_3146_0": {
      "display": true
    },
    "SkredSteinAktR_3146_1": {
      "display": true
    },
    "SkredSteinAktR_3146_2": {
      "display": true
    },
    "Flomsoner1_575": {
      "display": false
    },
    "Flomsoner1_575_0": {
      "display": true
    },
    "Flomsoner1_575_1": {
      "display": true
    },
    "Flomsoner1_575_2": {
      "display": true
    },
    "Flomsoner1_575_3": {
      "display": true
    },
    "Flomsoner1_575_4": {
      "display": true
    },
    "Flomsoner1_575_5": {
      "display": true
    },
    "Flomsoner1_575_6": {
      "display": true
    },
    "Flomsoner1_575_7": {
      "display": true
    },
    "Flomsoner1_575_8": {
      "display": true
    },
    "Flomsoner1_575_9": {
      "display": true
    },
    "Flomsoner1_575_10": {
      "display": true
    },
    "Flomsoner1_575_11": {
      "display": true
    },
    "Flomsoner1_575_12": {
      "display": true
    },
    "Flomsoner1_575_13": {
      "display": true
    },
    "Flomsoner1_575_14": {
      "display": true
    },
    "Flomsoner1_575_15": {
      "display": true
    },
    "Flomsoner1_575_16": {
      "display": true
    },
    "Flomsoner1_575_17": {
      "display": true
    },
    "Flomsoner1_575_18": {
      "display": true
    },
    "wms_8792": {
      "display": false
    },
    "wms_8792_andre_linjer_uten_hoyde": {
      "display": true
    },
    "wms_8792_andre_linjer_under_40m": {
      "display": true
    },
    "wms_8792_andre_linjer_mellom_40m_60m": {
      "display": true
    },
    "wms_8792_andre_linjer_60m_og_over": {
      "display": true
    },
    "wms_8792_kraftledning_uten_hoyde": {
      "display": true
    },
    "wms_8792_kraftledning_under_40m": {
      "display": true
    },
    "wms_8792_kraftledning_mellom_40m_60m": {
      "display": true
    },
    "wms_8792_kraftledning_60m_og_over": {
      "display": true
    },
    "wms_8792_linjepunkt_uten_hoyde": {
      "display": true
    },
    "wms_8792_linjepunkt_under_40m": {
      "display": true
    },
    "wms_8792_linjepunkt_mellom_40m_60m": {
      "display": true
    },
    "wms_8792_linjepunkt_60m_og_over": {
      "display": true
    },
    "wms_8792_kraftstolpe_uten_hoyde": {
      "display": true
    },
    "wms_8792_kraftstolpe_under_40m": {
      "display": true
    },
    "wms_8792_kraftstolpe_mellom_40m_60m": {
      "display": true
    },
    "wms_8792_kraftstolpe_60m_og_over": {
      "display": true
    },
    "wms_8792_punkthindre_uten_hoyde": {
      "display": true
    },
    "wms_8792_punkthindre_under_40m": {
      "display": true
    },
    "wms_8792_punkthindre_mellom_40m_60m": {
      "display": true
    },
    "wms_8792_Punkthindre_60m_og_over": {
      "display": true
    },
    "wms_9377": {
      "display": false
    },
    "wms_9377_privatveg": {
      "display": true
    },
    "wms_9377_skogsbilveg": {
      "display": true
    },
    "wms_9377_kommunalveg": {
      "display": true
    },
    "wms_9377_fylkesveg": {
      "display": true
    },
    "wms_9377_riksveg": {
      "display": true
    },
    "wms_9377_europaveg": {
      "display": true
    },
    "wms_9377_bilferjestrekning": {
      "display": true
    },
    "wms_9377_vegnavn": {
      "display": true
    },
    "wms_9157": {
      "display": false
    },
    "wms_9157_gang_og_sykkelveg": {
      "display": true
    },
    "wms_9157_sykkelveg": {
      "display": true
    },
    "wms_9157_fortau_og_frittstaende_trapp": {
      "display": true
    },
    "wms_1712": {
      "display": false
    },
    "wms_1712_spr_strandsoner": {
      "display": true
    },
    "wms_8916": {
      "display": false
    },
    "wms_8916_Arealformal_01": {
      "display": true
    },
    "wms_8916_Hensynsoner_bestemmelsesomrader_01": {
      "display": true
    },
    "wms_8916_Grenser_og_juridiske_linjer_01": {
      "display": true
    },
    "wms_8916_Planomrade_01": {
      "display": true
    },
    "wms_8916_Juridiske_punkter_01": {
      "display": true
    },
    "wms_8916_Paskrift_01": {
      "display": true
    },
    "wms_8916_Arealformal_02": {
      "display": true
    },
    "wms_8916_Hensynsoner_bestemmelsesomrader_02": {
      "display": true
    },
    "wms_8916_Grenser_og_juridiske_linjer_02": {
      "display": true
    },
    "wms_8916_Planomrade_02": {
      "display": true
    },
    "wms_8916_Juridiske_punkter_02": {
      "display": true
    },
    "wms_8916_Paskrift_02": {
      "display": true
    },
    "wms_9807": {
      "display": false
    },
    "wms_9807_Arealformal_01": {
      "display": true
    },
    "wms_9807_Hensynsoner_bestemmelsesomrader_01": {
      "display": true
    },
    "wms_9807_Grenser_og_juridiske_linjer_01": {
      "display": true
    },
    "wms_9807_Planomrade_01": {
      "display": true
    },
    "wms_9807_Juridiske_punkter_01": {
      "display": true
    },
    "wms_9807_Paskrift_01": {
      "display": true
    },
    "wms_9807_Arealformal_02": {
      "display": true
    },
    "wms_9807_Hensynsoner_bestemmelsesomrader_02": {
      "display": true
    },
    "wms_9807_Grenser_og_juridiske_linjer_02": {
      "display": true
    },
    "wms_9807_Planomrade_02": {
      "display": true
    },
    "wms_9807_Juridiske_punkter_02": {
      "display": true
    },
    "wms_9807_Paskrift_02": {
      "display": true
    },
    "wms_9807_Arealformal_03": {
      "display": true
    },
    "wms_9807_Hensynsoner_bestemmelsesomrader_03": {
      "display": true
    },
    "wms_9807_Grenser_og_juridiske_linjer_03": {
      "display": true
    },
    "wms_9807_Planomrade_03": {
      "display": true
    },
    "wms_9807_Juridiske_punkter_03": {
      "display": true
    },
    "wms_9807_Paskrift_03": {
      "display": true
    },
    "wms_9807_Arealformal_04": {
      "display": true
    },
    "wms_9807_Hensynsoner_bestemmelsesomrader_04": {
      "display": true
    },
    "wms_9807_Grenser_og_juridiske_linjer_04": {
      "display": true
    },
    "wms_9807_Planomrade_04": {
      "display": true
    },
    "wms_9807_Juridiske_punkter_04": {
      "display": true
    },
    "wms_9807_Paskrift_04": {
      "display": true
    },
    "wms_9807_Arealformal_05": {
      "display": true
    },
    "wms_9807_Hensynsoner_bestemmelsesomrader_05": {
      "display": true
    },
    "wms_9807_Grenser_og_juridiske_linjer_05": {
      "display": true
    },
    "wms_9807_Planomrade_05": {
      "display": true
    },
    "wms_9807_Juridiske_punkter_05": {
      "display": true
    },
    "wms_9807_Paskrift_05": {
      "display": true
    },
    "wms_5639": {
      "display": false
    },
    "wms_5639_friluftsomrade_01": {
      "display": true
    },
    "wms_5639_parkeringsomrader_friluft_01": {
      "display": true
    },
    "wms_5639_turvei_01": {
      "display": true
    },
    "wms_5639_turisthytte_01": {
      "display": true
    },
    "wms_5639_fiskeplass_01": {
      "display": true
    },
    "wms_5639_baderampe_01": {
      "display": true
    },
    "wms_5639_gapahukhytte_01": {
      "display": true
    },
    "wms_5639_grillbalplass_01": {
      "display": true
    },
    "wms_5639_sittegruppe_01": {
      "display": true
    },
    "wms_5639_toalett_01": {
      "display": true
    },
    "wms_5639_hc_parkering_friluft_01": {
      "display": true
    },
    "wms_5639_friluftsomrade_02": {
      "display": true
    },
    "wms_5639_parkeringsomrader_friluft_02": {
      "display": true
    },
    "wms_5639_turvei_02": {
      "display": true
    },
    "wms_5639_turisthytte_02": {
      "display": true
    },
    "wms_5639_fiskeplass_02": {
      "display": true
    },
    "wms_5639_gapahukhytte_02": {
      "display": true
    },
    "wms_5639_grillbalplass_02": {
      "display": true
    },
    "wms_5639_sittegruppe_02": {
      "display": true
    },
    "wms_5639_toalett_02": {
      "display": true
    },
    "wms_5639_hc_parkering_friluft_02": {
      "display": true
    },
    "wms_5639_friluftsomrade_03": {
      "display": true
    },
    "wms_5639_parkeringsomrader_friluft_03": {
      "display": true
    },
    "wms_5639_turvei_03": {
      "display": true
    },
    "wms_5639_turisthytte_03": {
      "display": true
    },
    "wms_5639_fiskeplass_03": {
      "display": true
    },
    "wms_5639_baderampe_02": {
      "display": true
    },
    "wms_5639_gapahukhytte_03": {
      "display": true
    },
    "wms_5639_grillbalplass_03": {
      "display": true
    },
    "wms_5639_sittegruppe_03": {
      "display": true
    },
    "wms_5639_toalett_03": {
      "display": true
    },
    "wms_5639_hc_parkering_friluft_03": {
      "display": true
    },
    "wms_6576": {
      "display": false
    },
    "wms_6576_t_parkeringsomrade_r": {
      "display": true
    },
    "wms_6576_t_vei_r": {
      "display": true
    },
    "wms_6576_t_HC_parkering_r": {
      "display": true
    },
    "wms_6576_t_inngangbygg_r_01": {
      "display": true
    },
    "wms_6576_t_parkeringsomrade_el": {
      "display": true
    },
    "wms_6576_t_vei_el": {
      "display": true
    },
    "wms_6576_t_HC_parkering_el": {
      "display": true
    },
    "wms_6576_t_inngangbygg_r_02": {
      "display": true
    },
    "wms_6576_t_parkeringsomrade": {
      "display": true
    },
    "wms_6576_t_vei": {
      "display": true
    },
    "wms_6576_t_HC_parkering": {
      "display": true
    },
    "wms_6576_t_inngangbygg": {
      "display": true
    },
    "wms_3069": {
      "display": false
    },
    "wms_3069_MarineLandskap": {
      "display": true
    },
    "wms_9784": {
      "display": false
    },
    "wms_9784_DD Presisjon": {
      "display": true
    },
    "wms_9784_DD_punkt": {
      "display": true
    },
    "wms_9784_NT Presisjon": {
      "display": true
    },
    "wms_9784_NT_punkt": {
      "display": true
    },
    "wms_9784_VU Presisjon": {
      "display": true
    },
    "wms_9784_VU_punkt": {
      "display": true
    },
    "wms_9784_EN Presisjon": {
      "display": true
    },
    "wms_9784_EN_punkt": {
      "display": true
    },
    "wms_9784_CR Presisjon": {
      "display": true
    },
    "wms_9784_CR_punkt": {
      "display": true
    },
    "wms_9784_RE Presisjon": {
      "display": true
    },
    "wms_9784_RE_punkt": {
      "display": true
    },
    "SvekketIs1_9111": {
      "display": false
    },
    "SvekketIs1_9111_0": {
      "display": true
    },
    "SvekketIs1_9111_1": {
      "display": true
    },
    "SvekketIs1_9111_2": {
      "display": true
    },
    "SvekketIs1_9111_3": {
      "display": true
    },
    "SvekketIs1_9111_4": {
      "display": true
    },
    "SvekketIs1_9111_5": {
      "display": true
    },
    "Innsjodatabase1_2475": {
      "display": false
    },
    "Innsjodatabase1_2475_0": {
      "display": true
    },
    "Innsjodatabase1_2475_1": {
      "display": true
    },
    "Innsjodatabase1_2475_2": {
      "display": true
    },
    "wms_7328": {
      "display": false
    },
    "wms_7328_Israndavsetninger": {
      "display": true
    },
    "wms_7328_Skjellsand_modellert": {
      "display": true
    },
    "wms_7328_Skjellsand_kartlagt": {
      "display": true
    },
    "wms_7328_Skjellsand_observasjon": {
      "display": true
    },
    "wms_7328_Skjellsand_datadekning": {
      "display": true
    },
    "wms_7328_Biotoper_MTRL": {
      "display": true
    },
    "wms_7328_Biotoper_NLVI": {
      "display": true
    },
    "wms_7328_Biotoper_T2N7": {
      "display": true
    },
    "wms_7328_Biotoper_Egk_TR3_FM": {
      "display": true
    },
    "HydrologiskeData1_9258": {
      "display": false
    },
    "HydrologiskeData1_9258_0": {
      "display": true
    },
    "HydrologiskeData1_9258_1": {
      "display": true
    },
    "HydrologiskeData1_9258_2": {
      "display": true
    },
    "HydrologiskeData1_9258_3": {
      "display": true
    },
    "HydrologiskeData1_9258_4": {
      "display": true
    },
    "Elvenett1_4768": {
      "display": false
    },
    "Elvenett1_4768_0": {
      "display": true
    },
    "Elvenett1_4768_1": {
      "display": true
    },
    "Elvenett1_4768_2": {
      "display": true
    },
    "VerneplanforVassdrag_8924": {
      "display": false
    },
    "VerneplanforVassdrag_8924_0": {
      "display": true
    },
    "wms_779": {
      "display": false
    },
    "wms_779_Jordbruksregioner": {
      "display": true
    },
    "wms_779_Landskapsregioner": {
      "display": true
    },
    "wms_779_Underregioner": {
      "display": true
    },
    "wms_4143": {
      "display": false
    },
    "wms_4143_Oversiktskart": {
      "display": true
    },
    "wms_4143_Vegetasjonstypar": {
      "display": true
    },
    "wms_4143_Kartsignatur": {
      "display": true
    },
    "wms_4143_Hovudtypar": {
      "display": true
    },
    "wms_4143_Saubeite": {
      "display": true
    },
    "wms_4143_Storfebeite": {
      "display": true
    },
    "wms_4143_Tilleggsinformasjon": {
      "display": true
    },
    "wms_4143_Naturtypar": {
      "display": true
    },
    "wms_2440": {
      "display": false
    },
    "wms_2440_Satellitt_infrarod": {
      "display": true
    },
    "wms_2440_Satellitt_naturlig": {
      "display": true
    },
    "wms_2440_Alder": {
      "display": true
    },
    "wms_2440_Dominerende_treslag": {
      "display": true
    },
    "wms_2440_Volum": {
      "display": true
    },
    "wms_2440_Volum_gran": {
      "display": true
    },
    "wms_2440_Volum_furu": {
      "display": true
    },
    "wms_2440_Volum_lauv": {
      "display": true
    },
    "wms_2440_Arstall": {
      "display": true
    },
    "wms_2440_Figurer": {
      "display": true
    },
    "wms_2440_Status_satskog": {
      "display": true
    },
    "wms_5552": {
      "display": false
    },
    "wms_5552_Vernskog": {
      "display": true
    },
    "wms_7531": {
      "display": false
    },
    "wms_7531_Nedbygd_jordbruksareal_flate": {
      "display": true
    },
    "wms_7531_Nedbygd_jordbruksareal_punkt": {
      "display": true
    },
    "wms_7737": {
      "display": false
    },
    "wms_7737_Jordkvalitet": {
      "display": true
    },
    "wms_1582": {
      "display": false
    },
    "wms_1582_Bonitet": {
      "display": true
    },
    "wms_1582_Arealtyper": {
      "display": true
    },
    "wms_1582_Skogbonitet": {
      "display": true
    },
    "wms_1582_Myr": {
      "display": true
    },
    "wms_1582_Treslag": {
      "display": true
    },
    "wms_1582_Dyrkbar_jord": {
      "display": true
    },
    "wms_1582_Jordbruk": {
      "display": true
    },
    "wms_1582_Snaumark": {
      "display": true
    },
    "wms_3754": {
      "display": false
    },
    "wms_3754_Bonitet": {
      "display": true
    },
    "wms_3754_Arealtyper": {
      "display": true
    },
    "wms_3754_Skogbonitet": {
      "display": true
    },
    "wms_3754_Myr": {
      "display": true
    },
    "wms_3754_Treslag": {
      "display": true
    },
    "wms_3754_Dyrkbar_jord": {
      "display": true
    },
    "wms_3754_Snaumark": {
      "display": true
    },
    "wms_4522": {
      "display": false
    },
    "wms_4522_Mattilsynet_Bigaardsplasser": {
      "display": true
    },
    "wms_4712": {
      "display": false
    },
    "wms_4712_Sau_per_km2": {
      "display": true
    },
    "wms_4712_Tapsprosent_storfe": {
      "display": true
    },
    "wms_4712_Tapsprosent_geit": {
      "display": true
    },
    "wms_4712_Tapsprosent_lam": {
      "display": true
    },
    "wms_4712_Tapsprosent_sau": {
      "display": true
    },
    "wms_4712_Tapsprosent_sau_lam": {
      "display": true
    },
    "wms_4712_Storfe_sleppt": {
      "display": true
    },
    "wms_4712_Geit_sleppt": {
      "display": true
    },
    "wms_4712_Lam_sleppt": {
      "display": true
    },
    "wms_4712_Sau_sleppt": {
      "display": true
    },
    "wms_4712_Sau_lam_sleppt": {
      "display": true
    },
    "wms_4712_Dyreslag": {
      "display": true
    },
    "wms_4712_Beitelaggrenser": {
      "display": true
    },
    "wms_4712_dyreslag_seter": {
      "display": true
    },
    "wms_4712_Seter": {
      "display": true
    },
    "wms_4712_Beitelagnamn": {
      "display": true
    },
    "wms_5372": {
      "display": false
    },
    "wms_5372_Losmasse_flate_N1000_web": {
      "display": true
    },
    "wms_5372_Losmasse_flate_N1000": {
      "display": true
    },
    "wms_5372_Losmasse_flate_label": {
      "display": true
    },
    "wms_5372_Losmasse_flate": {
      "display": true
    },
    "wms_5372_Losmasse_grense": {
      "display": true
    },
    "wms_5372_Losmasse_formlinje_N1000": {
      "display": true
    },
    "wms_5372_Saltvannsavsetning_N1000_web": {
      "display": true
    },
    "wms_5372_Saltvannsavsetning_N1000": {
      "display": true
    },
    "wms_5372_Saltvannsavsetning": {
      "display": true
    },
    "wms_5372_Mektighet_N1000_web": {
      "display": true
    },
    "wms_5372_Mektighet_N1000": {
      "display": true
    },
    "wms_5372_Mektighet": {
      "display": true
    },
    "wms_5372_Infiltrasjonsevne": {
      "display": true
    },
    "wms_5372_Grunnvannspotensiale": {
      "display": true
    },
    "wms_5372_Skredmateriale_N1000_web": {
      "display": true
    },
    "wms_5372_Skredmateriale_N1000": {
      "display": true
    },
    "wms_5372_Skredmateriale": {
      "display": true
    },
    "wms_9243": {
      "display": false
    },
    "wms_9243_Bergart_flate_oversikt": {
      "display": true
    },
    "wms_9243_Bergart_flate_N250": {
      "display": true
    },
    "wms_9243_Bergart_grense_N250": {
      "display": true
    },
    "wms_9243_Berggrunn_raster_N250_tegnforklaring": {
      "display": true
    },
    "wms_9243_Berggrunn_raster_N250_oversikt": {
      "display": true
    },
    "wms_9243_Berggrunn_raster_N250_detalj": {
      "display": true
    },
    "wms_9243_Lineamenter_satellittolket_N750": {
      "display": true
    },
    "wms_9243_Lineamenter_N250": {
      "display": true
    },
    "wms_3602": {
      "display": false
    },
    "wms_3602_Bergart_N50_dekning": {
      "display": true
    },
    "wms_3602_Bergart_N50_ikkekartlagt": {
      "display": true
    },
    "wms_3602_Bergart_flate_N50": {
      "display": true
    },
    "wms_3602_Bergart_grense_N50": {
      "display": true
    },
    "wms_6505": {
      "display": false
    },
    "wms_6505_Grus_Pukk_omrade_verdivurdering": {
      "display": true
    },
    "wms_6505_Grus_Pukk_registrering_verdivurdering": {
      "display": true
    },
    "wms_6505_Grus_Pukk_omrade": {
      "display": true
    },
    "wms_6505_Grus_Pukk_registrering": {
      "display": true
    },
    "wms_6505_Grus_Pukk_statistikkpunkt_nasjonal": {
      "display": true
    },
    "wms_6505_Grus_Pukk_statistikkpunkt_regional": {
      "display": true
    },
    "wms_6505_Grus_Pukk_provepunkt": {
      "display": true
    },
    "wms_6505_Grus_Pukk_observasjon": {
      "display": true
    },
    "wms_6505_Grus_Pukk_uttak": {
      "display": true
    },
    "wms_6505_Steintipp": {
      "display": true
    },
    "wms_8697": {
      "display": false
    },
    "wms_8697_Industrimineralomrade_-_Verdivurdering": {
      "display": true
    },
    "wms_8697_Forekomster": {
      "display": true
    },
    "wms_8697_Feltspatmineraler": {
      "display": true
    },
    "wms_8697_Pegmatitt_Feltspat": {
      "display": true
    },
    "wms_8697_Anortositt": {
      "display": true
    },
    "wms_8697_Feltspat_uspes": {
      "display": true
    },
    "wms_8697_Amazonitt": {
      "display": true
    },
    "wms_8697_Karbonatmineraler": {
      "display": true
    },
    "wms_8697_Kalkstein": {
      "display": true
    },
    "wms_8697_Dolomitt": {
      "display": true
    },
    "wms_8697_Karbonater_uspes": {
      "display": true
    },
    "wms_8697_Silika": {
      "display": true
    },
    "wms_8697_Kvartsitt": {
      "display": true
    },
    "wms_8697_Kvarts": {
      "display": true
    },
    "wms_8697_Kvarts_uspes": {
      "display": true
    },
    "wms_8697_Pegmatitt_Silika": {
      "display": true
    },
    "wms_8697_Olivinmineraler": {
      "display": true
    },
    "wms_8697_Ultramafitt_uspes": {
      "display": true
    },
    "wms_8697_Olivin": {
      "display": true
    },
    "wms_8697_Andre_mineraler": {
      "display": true
    },
    "wms_8697_Apatitt": {
      "display": true
    },
    "wms_8697_Flusspat": {
      "display": true
    },
    "wms_8697_Kyanitt": {
      "display": true
    },
    "wms_8697_Wollastonitt": {
      "display": true
    },
    "wms_8697_Glimmer": {
      "display": true
    },
    "wms_8697_Asbest": {
      "display": true
    },
    "wms_8697_Kiselgur": {
      "display": true
    },
    "wms_8697_Kaolin": {
      "display": true
    },
    "wms_8697_Barytt": {
      "display": true
    },
    "wms_8697_Granat": {
      "display": true
    },
    "wms_8697_Grafittmineraler": {
      "display": true
    },
    "wms_8697_Grafitt": {
      "display": true
    },
    "wms_8697_Talkmineraler": {
      "display": true
    },
    "wms_8697_Kalk_Kleberstein": {
      "display": true
    },
    "wms_8697_Kalk": {
      "display": true
    },
    "wms_8697_Serpentin": {
      "display": true
    },
    "wms_8697_Berylliummineraler": {
      "display": true
    },
    "wms_8697_Beryll": {
      "display": true
    },
    "wms_8697_Fenakitt": {
      "display": true
    },
    "wms_8697_Magnesiummineraler": {
      "display": true
    },
    "wms_8697_Magnesitt": {
      "display": true
    },
    "wms_8697_Brusitt": {
      "display": true
    },
    "wms_8697_Nefelinmineraler": {
      "display": true
    },
    "wms_8697_Nefelinsyenitt": {
      "display": true
    },
    "wms_8697_Zirkoniummineraler": {
      "display": true
    },
    "wms_8697_Zircon": {
      "display": true
    },
    "wms_8697_Baddeleyitt": {
      "display": true
    },
    "wms_8697_Kullmineraler": {
      "display": true
    },
    "wms_8697_Kull": {
      "display": true
    },
    "wms_4126": {
      "display": false
    },
    "wms_4126_Forekomster": {
      "display": true
    },
    "wms_4126_Basemetaller": {
      "display": true
    },
    "wms_4126_Antimon": {
      "display": true
    },
    "wms_4126_Arsen": {
      "display": true
    },
    "wms_4126_Vismut": {
      "display": true
    },
    "wms_4126_Kobber": {
      "display": true
    },
    "wms_4126_Bly": {
      "display": true
    },
    "wms_4126_Tinn": {
      "display": true
    },
    "wms_4126_Sink": {
      "display": true
    },
    "wms_4126_Jern-sulfider": {
      "display": true
    },
    "wms_4126_Jernmetaller": {
      "display": true
    },
    "wms_4126_Jern": {
      "display": true
    },
    "wms_4126_Jern-titan": {
      "display": true
    },
    "wms_4126_Mangan": {
      "display": true
    },
    "wms_4126_Titan": {
      "display": true
    },
    "wms_4126_Jernlegeringsmetaller": {
      "display": true
    },
    "wms_4126_Krom": {
      "display": true
    },
    "wms_4126_Cobolt": {
      "display": true
    },
    "wms_4126_Molybden": {
      "display": true
    },
    "wms_4126_Nikkel": {
      "display": true
    },
    "wms_4126_Vanadium": {
      "display": true
    },
    "wms_4126_Wolfram": {
      "display": true
    },
    "wms_4126_Edelmetaller": {
      "display": true
    },
    "wms_4126_Gull": {
      "display": true
    },
    "wms_4126_PGE": {
      "display": true
    },
    "wms_4126_Solv": {
      "display": true
    },
    "wms_4126_Energimetaller": {
      "display": true
    },
    "wms_4126_Thorium": {
      "display": true
    },
    "wms_4126_Uran": {
      "display": true
    },
    "wms_4126_Spesialmetaller": {
      "display": true
    },
    "wms_4126_Beryll": {
      "display": true
    },
    "wms_4126_Litium": {
      "display": true
    },
    "wms_4126_Niob": {
      "display": true
    },
    "wms_4126_REE": {
      "display": true
    },
    "wms_4126_Scandium": {
      "display": true
    },
    "wms_4126_Tantal": {
      "display": true
    },
    "wms_8332": {
      "display": false
    },
    "wms_8332_Natursteinsomrade_-_Verdivurdering": {
      "display": true
    },
    "wms_8332_Forekomster": {
      "display": true
    },
    "wms_8332_Skifer_og_hellestein": {
      "display": true
    },
    "wms_8332_Leirskifer": {
      "display": true
    },
    "wms_8332_Gronnskifer": {
      "display": true
    },
    "wms_8332_Glimmerskifer_Skiferstein": {
      "display": true
    },
    "wms_8332_Fyllitt": {
      "display": true
    },
    "wms_8332_Kvartsittskifer": {
      "display": true
    },
    "wms_8332_Skifer_Skiferstein": {
      "display": true
    },
    "wms_8332_Gneis_Skiferstein": {
      "display": true
    },
    "wms_8332_Amfibolitt": {
      "display": true
    },
    "wms_8332_Granitt_og_andre_storkningsbergarter": {
      "display": true
    },
    "wms_8332_Anortositt": {
      "display": true
    },
    "wms_8332_Gabbro": {
      "display": true
    },
    "wms_8332_Monsonitt": {
      "display": true
    },
    "wms_8332_Syenitt": {
      "display": true
    },
    "wms_8332_Larvikitt": {
      "display": true
    },
    "wms_8332_Granitt": {
      "display": true
    },
    "wms_8332_Trondhjemitt": {
      "display": true
    },
    "wms_8332_Kleberstein_og_serpentinitt": {
      "display": true
    },
    "wms_8332_Kleberstein": {
      "display": true
    },
    "wms_8332_Serpentinitt": {
      "display": true
    },
    "wms_8332_Marmor_og_kalkstein": {
      "display": true
    },
    "wms_8332_Marmor": {
      "display": true
    },
    "wms_8332_Kalkstein_Blokkstein": {
      "display": true
    },
    "wms_8332_Gneis": {
      "display": true
    },
    "wms_8332_Gneis_Blokkstein": {
      "display": true
    },
    "wms_8332_Sandstein_og_konglomerat": {
      "display": true
    },
    "wms_8332_Sandstein": {
      "display": true
    },
    "wms_8332_Konglomerat": {
      "display": true
    },
    "wms_8332_Kvartsitt_Blokkstein": {
      "display": true
    },
    "wms_8332_Breksje": {
      "display": true
    },
    "wms_8332_Brynestein": {
      "display": true
    },
    "wms_8332_Skifer_Brynestein": {
      "display": true
    },
    "wms_8332_Sandstein_Brynestein": {
      "display": true
    },
    "wms_8332_Kvartsitt_Brynestein": {
      "display": true
    },
    "wms_8332_Annen_blokkstein": {
      "display": true
    },
    "wms_8332_Eklogitt": {
      "display": true
    },
    "wms_8332_Kvernstein": {
      "display": true
    },
    "wms_8332_Glimmerskifer_Kvernstein": {
      "display": true
    },
    "wms_6192": {
      "display": true
    },
    "wms_6192_Radon_aktsomhet_oversikt": {
      "display": true
    },
    "wms_6192_Radon_aktsomhet": {
      "display": true
    },
    "wms_3116": {
      "display": false
    },
    "wms_3116_Fjellbronn_ukjent": {
      "display": true
    },
    "wms_3116_Fjellbronn_vannforsyning": {
      "display": true
    },
    "wms_3116_Fjellbronn_energi": {
      "display": true
    },
    "wms_3116_Sonderboring": {
      "display": true
    },
    "wms_3116_Losmassebronn_ukjent": {
      "display": true
    },
    "wms_3116_Losmassebronn_vannforsyning": {
      "display": true
    },
    "wms_3116_Losmassebronn_undersokelse": {
      "display": true
    },
    "wms_3116_Fjellbronn_undersokelse": {
      "display": true
    },
    "wms_3116_Losmassebronn_energi": {
      "display": true
    },
    "wms_3116_LGN": {
      "display": true
    },
    "wms_3116_Kilde_losmasse": {
      "display": true
    },
    "wms_3116_Kilde_fjell": {
      "display": true
    },
    "wms_3116_Grunnvannspunkter_nasjonal": {
      "display": true
    },
    "wms_3116_Grunnvannspunkter_regional": {
      "display": true
    },
    "wms_4486": {
      "display": false
    },
    "wms_4486_Natursti": {
      "display": true
    },
    "wms_4486_Kultursti": {
      "display": true
    },
    "wms_4486_Kyststi": {
      "display": true
    },
    "wms_4486_Historisk": {
      "display": true
    },
    "wms_6067": {
      "display": false
    },
    "wms_6067_Skiloype": {
      "display": true
    },
    "wms_6067_Skiloype_gradering_ikke_angitt": {
      "display": true
    },
    "wms_6067_Skiloype_ingen_gradering": {
      "display": true
    },
    "wms_6067_Enkel_skiloype": {
      "display": true
    },
    "wms_6067_Middels_skiloype": {
      "display": true
    },
    "wms_6067_Krevende_skiloype": {
      "display": true
    },
    "wms_6067_Ekspert_skiloype": {
      "display": true
    },
    "wms_6016": {
      "display": false
    },
    "wms_6016_Fotrute": {
      "display": true
    },
    "wms_6016_Fotrutetypeikkeangitt": {
      "display": true
    },
    "wms_6016_Fotrute_gradering_ikke_angitt": {
      "display": true
    },
    "wms_6016_Fotrute_ingen_gradering": {
      "display": true
    },
    "wms_6016_Enkel_fotrute": {
      "display": true
    },
    "wms_6016_Middels_fotrute": {
      "display": true
    },
    "wms_6016_Krevende_fotrute": {
      "display": true
    },
    "wms_6016_Ekspert_fotrute": {
      "display": true
    },
    "wms_4183": {
      "display": false
    },
    "wms_4183_Sykkelrute": {
      "display": true
    },
    "wms_4183_Sykkelrute_gradering_ikke_angitt": {
      "display": true
    },
    "wms_4183_Sykkelrute_ingen_gradering": {
      "display": true
    },
    "wms_4183_Enkel_sykkelrute": {
      "display": true
    },
    "wms_4183_Middels_sykkelrute": {
      "display": true
    },
    "wms_4183_Krevende_sykkelrute": {
      "display": true
    },
    "wms_4183_Ekspert_sykkelrute": {
      "display": true
    },
    "wms_4786": {
      "display": false
    },
    "wms_4786_okartnofpoly": {
      "display": true
    },
    "wms_4786_kartgrenser": {
      "display": true
    },
    "wms_4786_okartnof": {
      "display": true
    },
    "wms_4786_okartkriss": {
      "display": true
    },
    "wms_9232": {
      "display": true
    },
    "wms_9232_mareano_kjemi:BDE209": {
      "display": true
    },
    "wms_9232_mareano_kjemi:antracen": {
      "display": true
    },
    "wms_9232_mareano_kjemi:benzapyren": {
      "display": true
    },
    "wms_9232_mareano_kjemi:fenantren": {
      "display": true
    },
    "industri_2481": {
      "display": true
    },
    "industri_2481_0": {
      "display": true
    },
    "wms_7092": {
      "display": true
    },
    "wms_7092_marineanimalscesium137": {
      "display": true
    },
    "wms_7092_seawateramericium241": {
      "display": true
    },
    "wms_7092_seawatercesium137": {
      "display": true
    },
    "wms_7092_seawaterplutonium238": {
      "display": true
    },
    "wms_7092_seawaterplutonium239": {
      "display": true
    },
    "wms_7092_seawaterpolonium210": {
      "display": true
    },
    "wms_7092_seawaterstrontium90": {
      "display": true
    },
    "wms_7092_seawatertechnetium99": {
      "display": true
    },
    "wms_7092_seaweedcesium137": {
      "display": true
    },
    "wms_7092_seaweedtechnetium99": {
      "display": true
    },
    "wms_7092_sedimentscesium137": {
      "display": true
    },
    "Vannkraft1_8755": {
      "display": false
    },
    "Vannkraft1_8755_0": {
      "display": true
    },
    "Vannkraft1_8755_1": {
      "display": true
    },
    "Vannkraft1_8755_8": {
      "display": true
    },
    "Vannkraft1_8755_10": {
      "display": true
    },
    "Vindkraft_3444": {
      "display": false
    },
    "Vindkraft_3444_0": {
      "display": true
    },
    "Vindkraft_3444_1": {
      "display": true
    },
    "Vindkraft_3444_2": {
      "display": true
    },
    "Vindkraft_3444_3": {
      "display": true
    },
    "Vindkraft_3444_4": {
      "display": true
    },
    "Vindkraft_3444_5": {
      "display": true
    },
    "Vindkraft_3444_6": {
      "display": true
    },
    "wms_8038": {
      "display": false
    },
    "wms_8038_biogeografiske_regioner_grense": {
      "display": true
    },
    "wms_8038_biogeografiske_regioner_omrade": {
      "display": true
    },
    "wms_7889": {
      "display": false
    },
    "wms_7889_layer_21": {
      "display": true
    },
    "wms_4069": {
      "display": false
    },
    "wms_4069_marin_vp_ikke_oppstart": {
      "display": true
    },
    "wms_4069_marin_vp_oppstart": {
      "display": true
    },
    "wms_6276": {
      "display": false
    },
    "wms_6276_svo_barentshavet": {
      "display": true
    },
    "wms_6276_svo_nordsjoen": {
      "display": true
    },
    "wms_6276_svo_norskehavet": {
      "display": true
    },
    "wms_3991": {
      "display": true
    },
    "wms_3991_forurenset_omrade_tilstand": {
      "display": true
    },
    "wms_3991_forurenset_omrade_tilstand_pkt": {
      "display": true
    },
    "wms_3991_forurenset_omrade": {
      "display": true
    },
    "wms_3991_forurenset_omrade_pkt": {
      "display": true
    },
    "wms_9402": {
      "display": false
    },
    "wms_9402_svo_grense": {
      "display": true
    },
    "wms_9402_svo_omrade": {
      "display": true
    },
    "wms_7507": {
      "display": true
    },
    "wms_7507_petroleumsvirksomhet": {
      "display": true
    },
    "wms_9027": {
      "display": false
    },
    "wms_9027_bjorn_forvaltningsomrade": {
      "display": true
    },
    "wms_9027_gaupe_forvaltningsomrade": {
      "display": true
    },
    "wms_9027_jerv_forvaltningsomrade": {
      "display": true
    },
    "wms_9027_ulv_forvaltningsomrade": {
      "display": true
    },
    "wms_6424": {
      "display": false
    },
    "wms_6424_friluftsliv_kartlagt_faktaark": {
      "display": true
    },
    "wms_6424_friluftsliv_kartlagt_omrtype": {
      "display": true
    },
    "wms_6424_friluftsliv_kartlagt_verdi": {
      "display": true
    },
    "wms_1677": {
      "display": false
    },
    "wms_1677_kostholdsrad_omrade": {
      "display": true
    },
    "wms_1677_kostholdsrad_sted": {
      "display": true
    },
    "wms_5984": {
      "display": false
    },
    "wms_5984_kart": {
      "display": true
    },
    "wms_5984_precipitation_1h_regional": {
      "display": true
    },
    "wms_5984_surface_pressure_regional": {
      "display": true
    },
    "wms_5984_temperature_2m_regional": {
      "display": true
    },
    "wms_5984_wind_10m_regional": {
      "display": true
    },
    "wms_5984_ec.precip_6h": {
      "display": true
    },
    "wms_5984_ec.mslp": {
      "display": true
    },
    "wms_5984_ec.t2m": {
      "display": true
    },
    "wms_5984_ec.wind10m": {
      "display": true
    },
    "wms_5984_sea_wave_height_direction_regional": {
      "display": true
    },
    "wms_5984_sea_current_regional": {
      "display": true
    },
    "wms_5984_sea_salinity_regional": {
      "display": true
    },
    "wms_5984_sea_temperature_regional": {
      "display": true
    },
    "wms_5984_sea_surface_height_regional": {
      "display": true
    },
    "wms_5984_osisaf.icetype": {
      "display": true
    },
    "wms_5984_osisaf.iceedge": {
      "display": true
    },
    "wms_5984_osisaf.iceconcentration": {
      "display": true
    },
    "wms_5984_myocean.sst": {
      "display": true
    },
    "wms_5984_ice.ice_chart": {
      "display": true
    },
    "wms_5984_ice.ice_analysis_skagerak": {
      "display": true
    },
    "wms_5984_ice.ice_analysis_sar": {
      "display": true
    },
    "wms_5984_radar_precipitation_intensity": {
      "display": true
    },
    "wms_5984_ecmwf.swell": {
      "display": true
    },
    "wms_5984_ecmwf.wave": {
      "display": true
    },
    "wms_5984_sat.neuropa": {
      "display": true
    },
    "wms_5984_sat.npolen": {
      "display": true
    },
    "wms_5984_sat.natlant": {
      "display": true
    },
    "wms_5984_sat.ishavet": {
      "display": true
    },
    "wms_5984_wamws.windspeed.mean": {
      "display": true
    },
    "wms_5984_wamws.windspeed.10mps": {
      "display": true
    },
    "wms_5984_wamws.windspeed.15mps": {
      "display": true
    },
    "wms_5984_wamws.windspeed.20mps": {
      "display": true
    },
    "wms_5984_wamhs.hs.mean": {
      "display": true
    },
    "wms_5984_wamhs.freq2m": {
      "display": true
    },
    "wms_5984_wamhs.freq3m": {
      "display": true
    },
    "wms_5984_wamhs.freq4m": {
      "display": true
    },
    "wms_5984_wamhs.freq5m": {
      "display": true
    },
    "wms_5984_wamhs.freq6m": {
      "display": true
    },
    "wms_5984_wamws.windspeed.mean.year": {
      "display": true
    },
    "wms_5984_wamws.windspeed.10mps.year": {
      "display": true
    },
    "wms_5984_wamws.windspeed.15mps.year": {
      "display": true
    },
    "wms_5984_wamws.windspeed.20mps.year": {
      "display": true
    },
    "wms_5984_wamhs.hs.mean.year": {
      "display": true
    },
    "wms_5984_wamhs.freq2m.year": {
      "display": true
    },
    "wms_5984_wamhs.freq3m.year": {
      "display": true
    },
    "wms_5984_wamhs.freq4m.year": {
      "display": true
    },
    "wms_5984_wamhs.freq5m.year": {
      "display": true
    },
    "wms_5984_wamhs.freq6m.year": {
      "display": true
    },
    "wms_5984_iskart.konsentrasjon": {
      "display": true
    },
    "wms_5984_strike_probability": {
      "display": true
    },
    "wms_6148": {
      "display": false
    },
    "wms_6148_Mattilsynet_Vannverk_Inntakspunkter": {
      "display": true
    },
    "wms_8127": {
      "display": false
    },
    "wms_8127_Mattilsynet_Dyrehold_Produksjonsdyr": {
      "display": true
    },
    "wms_8178": {
      "display": false
    },
    "wms_8178_layer_151": {
      "display": true
    },
    "wms_8178_layer_152": {
      "display": true
    },
    "wms_4495": {
      "display": false
    },
    "wms_4495_layer_37": {
      "display": true
    },
    "wms_4495_layer_40": {
      "display": true
    },
    "wms_4495_layer_41": {
      "display": true
    },
    "wms_5526": {
      "display": false
    },
    "wms_5526_layer_363": {
      "display": true
    },
    "wms_1052": {
      "display": false
    },
    "wms_1052_layer_388": {
      "display": true
    },
    "wms_6774": {
      "display": false
    },
    "wms_6774_layer_264": {
      "display": true
    },
    "wms_6774_layer_265": {
      "display": true
    },
    "wms_5265": {
      "display": false
    },
    "wms_5265_layer_353": {
      "display": true
    },
    "wms_5265_layer_351": {
      "display": true
    },
    "wms_1686": {
      "display": false
    },
    "wms_1686_layer_202": {
      "display": true
    },
    "wms_1686_layer_203": {
      "display": true
    },
    "wms_1686_layer_263": {
      "display": true
    },
    "wms_1686_layer_364": {
      "display": true
    },
    "wms_1686_layer_262": {
      "display": true
    },
    "NFSSistOperativ_74": {
      "display": false
    },
    "NFSSistOperativ_74_0": {
      "display": true
    },
    "NFSSistOperativ_74_1": {
      "display": true
    },
    "NFSSistOperativ_74_2": {
      "display": true
    },
    "NFSSistOperativ_74_3": {
      "display": true
    },
    "NFSSistOperativ_74_4": {
      "display": true
    },
    "NFSSistOperativ_74_5": {
      "display": true
    },
    "NFSSistOperativ_74_6": {
      "display": true
    },
    "NFSSistOperativ_74_7": {
      "display": true
    },
    "NFSSistOperativ_74_8": {
      "display": true
    },
    "NFSSistOperativ_74_9": {
      "display": true
    },
    "NFSSistOperativ_74_10": {
      "display": true
    },
    "NFSSistOperativ_74_11": {
      "display": true
    },
    "NFSSistOperativ_74_12": {
      "display": true
    },
    "NFSSistOperativ_74_13": {
      "display": true
    },
    "NFSSistOperativ_74_14": {
      "display": true
    },
    "NFSSistOperativ_74_15": {
      "display": true
    },
    "NFSSistOperativ_74_16": {
      "display": true
    },
    "NFSSistOperativ_74_17": {
      "display": true
    },
    "NFSSistOperativ_74_18": {
      "display": true
    },
    "NFSSistOperativ_74_19": {
      "display": true
    },
    "wms_7094": {
      "display": false
    },
    "wms_7094_layer_190": {
      "display": true
    },
    "wms_7094_layer_185": {
      "display": true
    },
    "wms_1878": {
      "display": false
    },
    "wms_1878_layer_186": {
      "display": true
    },
    "wms_1878_layer_189": {
      "display": true
    },
    "wms_308": {
      "display": false
    },
    "wms_308_layer_183": {
      "display": true
    },
    "wms_308_layer_184": {
      "display": true
    },
    "wms_308_layer_179": {
      "display": true
    },
    "Bergrettigheter_9522": {
      "display": false
    },
    "Bergrettigheter_9522_0": {
      "display": true
    },
    "wms_6546": {
      "display": false
    },
    "wms_6546_Skytefelt": {
      "display": true
    },
    "wms_2850": {
      "display": false
    },
    "wms_2850_Stoyvarselkart": {
      "display": true
    },
    "wms_2850_Strategiskstoykart_lden": {
      "display": true
    },
    "wms_2850_Strategiskstoykart_lnight": {
      "display": true
    },
    "wms_9526": {
      "display": false
    },
    "wms_9526_stoylufthavn": {
      "display": true
    },
    "wms_7435": {
      "display": false
    },
    "wms_7435_stoyskytebane": {
      "display": true
    },
    "wms_1624": {
      "display": false
    },
    "wms_1624_0": {
      "display": true
    },
    "wms_1624_1": {
      "display": true
    },
    "wms_1624_2": {
      "display": true
    },
    "wms_1624_3": {
      "display": true
    },
    "wms_1624_4": {
      "display": true
    },
    "wms_1624_5": {
      "display": true
    },
    "wms_1624_6": {
      "display": true
    },
    "wms_1624_7": {
      "display": true
    },
    "wms_2322": {
      "display": false
    },
    "wms_2322_0": {
      "display": true
    },
    "wms_5159": {
      "display": false
    },
    "wms_5159_0": {
      "display": true
    },
    "wms_5159_1": {
      "display": true
    },
    "wms_5159_2": {
      "display": true
    },
    "wms_5159_3": {
      "display": true
    },
    "wms_4889": {
      "display": false
    },
    "wms_4889_Kystkontur_Generalisert": {
      "display": true
    },
    "wms_4889_Skjaer_Generalisert": {
      "display": true
    },
    "wms_4889_Kystkontur": {
      "display": true
    },
    "wms_4889_Skjaer": {
      "display": true
    },
    "NP_Basiskart_Svalbard_WMS_6104": {
      "display": false
    },
    "NP_Basiskart_Svalbard_WMS_6104_0": {
      "display": true
    },
    "NP_Basiskart_Svalbard_WMS_6104_1": {
      "display": true
    },
    "NP_Basiskart_Svalbard_WMS_6104_2": {
      "display": true
    },
    "NP_Basiskart_Svalbard_WMS_6104_3": {
      "display": true
    },
    "NP_Basiskart_Svalbard_WMS_6104_4": {
      "display": true
    },
    "NP_Basiskart_Svalbard_WMS_6104_5": {
      "display": true
    },
    "NP_Basiskart_Svalbard_WMS_6104_6": {
      "display": true
    },
    "NP_Basiskart_Svalbard_WMS_6104_7": {
      "display": true
    },
    "NP_Basiskart_Svalbard_WMS_6104_8": {
      "display": true
    },
    "NP_Basiskart_Svalbard_WMS_6104_9": {
      "display": true
    },
    "NP_Basiskart_Svalbard_WMS_6104_10": {
      "display": true
    },
    "NP_Basiskart_Svalbard_WMS_6104_11": {
      "display": true
    },
    "NP_Basiskart_Svalbard_WMS_6104_12": {
      "display": true
    },
    "NP_Basiskart_Svalbard_WMS_6104_13": {
      "display": true
    },
    "NP_Basiskart_Svalbard_WMS_6104_14": {
      "display": true
    },
    "NP_Basiskart_Svalbard_WMS_6104_15": {
      "display": true
    },
    "NP_Basiskart_Svalbard_WMS_6104_16": {
      "display": true
    },
    "NP_Basiskart_Svalbard_WMS_6104_17": {
      "display": true
    },
    "NP_Basiskart_Svalbard_WMS_6104_18": {
      "display": true
    },
    "NP_Basiskart_Svalbard_WMS_6104_19": {
      "display": true
    },
    "NP_Basiskart_Svalbard_WMS_6104_20": {
      "display": true
    },
    "NP_Basiskart_Svalbard_WMS_6104_21": {
      "display": true
    },
    "NP_Basiskart_Svalbard_WMS_6104_22": {
      "display": true
    },
    "NP_Basiskart_Svalbard_WMS_6104_23": {
      "display": true
    },
    "NP_Basiskart_Svalbard_WMS_6104_24": {
      "display": true
    },
    "NP_Basiskart_Svalbard_WMS_6104_25": {
      "display": true
    },
    "NP_Basiskart_Svalbard_WMS_6104_26": {
      "display": true
    },
    "NP_Basiskart_Svalbard_WMS_6104_27": {
      "display": true
    },
    "NP_Basiskart_Svalbard_WMS_6104_28": {
      "display": true
    },
    "NP_Basiskart_Svalbard_WMS_6104_29": {
      "display": true
    },
    "NP_Basiskart_Svalbard_WMS_6104_30": {
      "display": true
    },
    "NP_Basiskart_Svalbard_WMS_6104_31": {
      "display": true
    },
    "NP_Basiskart_Svalbard_WMS_6104_32": {
      "display": true
    },
    "NP_Basiskart_Svalbard_WMS_6104_33": {
      "display": true
    },
    "NP_Basiskart_Svalbard_WMS_6104_34": {
      "display": true
    },
    "NP_Basiskart_Svalbard_WMS_6104_35": {
      "display": true
    },
    "NP_Basiskart_Svalbard_WMS_6104_36": {
      "display": true
    },
    "NP_Basiskart_Svalbard_WMS_6104_37": {
      "display": true
    },
    "NP_Basiskart_Svalbard_WMS_6104_38": {
      "display": true
    },
    "NP_Basiskart_Svalbard_WMS_6104_39": {
      "display": true
    },
    "NP_Basiskart_Svalbard_WMS_6104_40": {
      "display": true
    },
    "NP_Basiskart_Svalbard_WMS_6104_41": {
      "display": true
    },
    "NP_Basiskart_Svalbard_WMS_6104_42": {
      "display": true
    },
    "NP_Basiskart_Svalbard_WMS_6104_43": {
      "display": true
    },
    "NP_Basiskart_Svalbard_WMS_6104_44": {
      "display": true
    },
    "NP_Basiskart_Svalbard_WMS_6104_45": {
      "display": true
    },
    "NP_Basiskart_JanMayen_WMS_45": {
      "display": false
    },
    "NP_Basiskart_JanMayen_WMS_45_0": {
      "display": true
    },
    "NP_Basiskart_JanMayen_WMS_45_1": {
      "display": true
    },
    "NP_Basiskart_JanMayen_WMS_45_2": {
      "display": true
    },
    "NP_Basiskart_JanMayen_WMS_45_3": {
      "display": true
    },
    "NP_Basiskart_JanMayen_WMS_45_4": {
      "display": true
    },
    "NP_Basiskart_JanMayen_WMS_45_5": {
      "display": true
    },
    "NP_Basiskart_JanMayen_WMS_45_6": {
      "display": true
    },
    "NP_Basiskart_JanMayen_WMS_45_7": {
      "display": true
    },
    "NP_Basiskart_JanMayen_WMS_45_8": {
      "display": true
    },
    "NP_Basiskart_JanMayen_WMS_45_9": {
      "display": true
    },
    "NP_Basiskart_JanMayen_WMS_45_10": {
      "display": true
    },
    "NP_Basiskart_JanMayen_WMS_45_11": {
      "display": true
    },
    "NP_Basiskart_JanMayen_WMS_45_12": {
      "display": true
    },
    "NP_Basiskart_JanMayen_WMS_45_13": {
      "display": true
    },
    "NP_Basiskart_JanMayen_WMS_45_14": {
      "display": true
    },
    "NP_Basiskart_JanMayen_WMS_45_15": {
      "display": true
    },
    "NP_Basiskart_JanMayen_WMS_45_16": {
      "display": true
    },
    "NP_Basiskart_JanMayen_WMS_45_17": {
      "display": true
    },
    "NP_Basiskart_JanMayen_WMS_45_18": {
      "display": true
    },
    "NP_Basiskart_JanMayen_WMS_45_19": {
      "display": true
    },
    "NP_Basiskart_JanMayen_WMS_45_20": {
      "display": true
    },
    "NP_Basiskart_JanMayen_WMS_45_21": {
      "display": true
    },
    "NP_Basiskart_JanMayen_WMS_45_22": {
      "display": true
    },
    "NP_Basiskart_JanMayen_WMS_45_23": {
      "display": true
    },
    "NP_Basiskart_JanMayen_WMS_45_24": {
      "display": true
    },
    "NP_Basiskart_JanMayen_WMS_45_25": {
      "display": true
    },
    "NP_Basiskart_JanMayen_WMS_45_26": {
      "display": true
    },
    "wms_2914": {
      "display": false
    },
    "wms_2914_dtm1_33": {
      "display": true
    },
    "wms_8963": {
      "display": false
    },
    "wms_8963_dtm10_33": {
      "display": true
    },
    "wms_3718": {
      "display": false
    },
    "wms_3718_dom10_33": {
      "display": true
    },
    "wms_4783": {
      "display": false
    },
    "wms_4783_Kommunegrenser": {
      "display": true
    },
    "wms_4783_Fylkesnavn": {
      "display": true
    },
    "wms_4783_Fylkesgrenser": {
      "display": true
    },
    "wms_4783_Kommunenavn": {
      "display": true
    },
    "wms_4783_Kommunenummer": {
      "display": true
    },
    "wms_913": {
      "display": false
    },
    "wms_913_Marka": {
      "display": true
    }
  }
}